cli.py
ensure_json.py
ensure_json-0.1.1.dist-info/METADATA
ensure_json-0.1.1.dist-info/WHEEL
ensure_json-0.1.1.dist-info/entry_points.txt
ensure_json-0.1.1.dist-info/top_level.txt
ensure_json-0.1.1.dist-info/RECORD
