Metadata-Version: 2.4
Name: ensure-json
Version: 0.1.1
Summary: A <3kB, dependency-free toolkit to repair 'almost-JSON' text from LLMs and return a valid Python object—or raise JsonFixError.
Author: 
License: MIT
Classifier: Programming Language :: Python :: 3
Classifier: License :: OSI Approved :: MIT License
Classifier: Operating System :: OS Independent
Requires-Python: >=3.7
Provides-Extra: schema
Requires-Dist: pydantic>=1.10.0; extra == "schema"
Dynamic: classifier
Dynamic: description
Dynamic: description-content-type
Dynamic: license
Dynamic: provides-extra
Dynamic: requires-python
Dynamic: summary
